pyReconcile/Scheduler.py
pyReconcile/__init__.py
pyReconcile/config/__init__.py
pyReconcile/config/logging.py
pyReconcile/mixins/Action.py
pyReconcile/mixins/Context.py
pyReconcile/mixins/DeclarativeState.py
pyReconcile/mixins/Plan.py
pyReconcile/mixins/__init__.py
pyReconcile-0.0.3.dist-info/LICENSE
pyReconcile-0.0.3.dist-info/METADATA
pyReconcile-0.0.3.dist-info/WHEEL
pyReconcile-0.0.3.dist-info/top_level.txt
pyReconcile-0.0.3.dist-info/RECORD
