Metadata-Version: 2.1
Name: pyReconcile
Version: 0.0.3
Summary: A reconciliation loop system.
Home-page: https://gitlab.com/cunruh3760/pyreconcile
Author: Charles Unruh
Author-email: charles.unruh.dev@gmail.com
License: UNKNOWN
Platform: UNKNOWN
Classifier: Programming Language :: Python :: 3
Classifier: License :: OSI Approved :: Mozilla Public License 2.0 (MPL 2.0)
Classifier: Operating System :: OS Independent
Classifier: Development Status :: 4 - Beta
Classifier: Natural Language :: English
Classifier: Topic :: Software Development :: Libraries
Requires-Python: >=3.6.8
Requires-Dist: deepdiff (==5.2.2)
